{"id":"10292","name":"Burnt Beaver","transitionsToward":[{"actorID":"8989","targetID":"82","newActorID":"10292","newTargetID":"82","targetRemains":true,"hand":true},{"actorID":"8989","targetID":"83","newActorID":"10292","newTargetID":"83","targetRemains":true,"hand":true},{"actorID":"8989","targetID":"3029","newActorID":"10292","newTargetID":"3029","targetRemains":true,"hand":true},{"actorID":"8989","targetID":"346","newActorID":"10292","newTargetID":"346","targetRemains":true,"hand":true}],"transitionsAway":[{"targetID":"10292","newActorID":"10293","newTargetID":"852","hand":true}],"transitionsTimed":[{"targetID":"10292","newTargetID":"852","decay":"3m"}],"version":"20290","craftable":false,"minPickupAge":3,"sounds":[270],"techTree":[{"id":"8989","nodes":[{"id":"139","nodes":[{"id":"138","nodes":[]}]},{"id":"11528","nodes":[{"id":"10290","nodes":[]},{"id":"10290","nodes":[]}]}]},{"id":"82","nodes":[{"id":"72","nodes":[{"id":"71","nodes":[]},{"id":"132","nodes":[]}]},{"id":"80","nodes":[{"decay":"5s"},{"id":"6518","nodes":[]}]}]}]}