{"id":"31","name":"Gooseberry","transitionsToward":[{"targetID":"30","newTargetUses":"-1","newActorID":"31","newTargetID":"30","targetRemains":true,"hand":true},{"targetID":"30","targetUses":"last","newActorID":"31","newTargetID":"279","hand":true},{"targetID":"253","newTargetUses":"-1","newActorID":"31","newTargetID":"253","targetRemains":true,"hand":true},{"targetID":"253","targetUses":"last","newActorID":"31","newTargetID":"235","hand":true},{"targetID":"391","newTargetUses":"-1","newActorID":"31","newTargetID":"391","targetRemains":true,"hand":true},{"targetID":"391","targetUses":"last","newActorID":"31","newTargetID":"1135","hand":true}],"transitionsAway":[{"actorID":"8709","newActorUses":"-1","newActorWeight":0.08,"targetID":"31","newActorID":"8709","newTargetID":"35","hand":true,"tool":true},{"actorID":"8709","actorUses":"last","targetID":"31","newActorID":"12012","newTargetID":"35","hand":true},{"actorID":"31","targetID":"235","newTargetUses":"last","newTargetID":"253","hand":true},{"actorID":"31","targetID":"253","newTargetUses":"+1","newTargetID":"253","targetRemains":true,"hand":true},{"actorID":"31","targetID":"2434","newTargetID":"2433","hand":true},{"actorID":"31","targetID":"2432","newTargetID":"2431","hand":true},{"actorID":"31","targetID":"2430","newTargetID":"2429","hand":true},{"actorID":"11671","newActorUses":"-1","newActorWeight":0.08,"targetID":"31","newActorID":"11671","newTargetID":"35","hand":true,"tool":true},{"actorID":"11671","actorUses":"last","targetID":"31","newActorID":"11560","newTargetID":"35","hand":true},{"actorID":"31","targetID":"8249","newTargetID":"8250","hand":true},{"actorID":"560","newActorUses":"-1","newActorWeight":0.04,"targetID":"31","newActorID":"560","newTargetID":"35","hand":true,"tool":true},{"actorID":"560","actorUses":"last","targetID":"31","newActorID":"11907","newTargetID":"35","hand":true}],"transitionsTimed":[{"targetID":"31","decay":"5m"}],"version":"16","foodValue":[1,0],"craftable":true,"depth":1,"size":1,"minPickupAge":3,"sounds":[147,41],"techTree":[{"id":"30","nodes":null}],"recipe":{"steps":[[{"id":"31","mainBranch":true,"depth":0,"targetID":"30","hand":true}]],"ingredients":["30"]}}