{
  "id": "237",
  "date": "2019-05-30T06:14:57.000Z",
  "commits": [
    {
      "sha": "09812a1ab458d5e2529a6214f7f6d1c6bd26b1ff",
      "message": "Can turn slot box into sledge to move it losslessly.  Note that excess items will scatter if you do this.",
      "date": "2019-05-30T04:32:57.000Z",
      "addedTransitions": [
        {
          "actorID": "67",
          "targetID": "3064",
          "newTargetID": "471",
          "hand": true
        },
        {
          "actorID": "67",
          "targetID": "3065",
          "newActorID": "58",
          "newTargetID": "471",
          "hand": true
        }
      ]
    }
  ]
}